fixtures/__init__.py
fixtures/empty_module.py
fixtures/lambda_app/__init__.py
fixtures/lambda_app/app_index.py
fixtures/lambda_app/functions/__init__.py
fixtures/lambda_app/functions/empty_controller/__init__.py
fixtures/lambda_app/functions/empty_controller/handler.py
fixtures/lambda_app/functions/fake_lambda_proxy_controller/__init__.py
fixtures/lambda_app/functions/fake_lambda_proxy_controller/handler.py
tight/__init__.py
tight/core/__init__.py
tight/core/logger.py
tight/core/safeget.py
tight/core/test_helpers.py
tight/providers/__init__.py
tight/providers/aws/__init__.py
tight/providers/aws/clients/__init__.py
tight/providers/aws/clients/boto3_client.py
tight/providers/aws/clients/dynamo_db.py
tight/providers/aws/controllers/__init__.py
tight/providers/aws/controllers/lambda_proxy_event.py
tight/providers/aws/lambda_app/__init__.py
tight/providers/aws/lambda_app/app.py
tight-0.1.0.dist-info/DESCRIPTION.rst
tight-0.1.0.dist-info/METADATA
tight-0.1.0.dist-info/RECORD
tight-0.1.0.dist-info/WHEEL
tight-0.1.0.dist-info/metadata.json
tight-0.1.0.dist-info/top_level.txt
