Metadata-Version: 1.1
Name: tight
Version: 0.1.0
Summary: Microframework
Home-page: https://github.com/michaelorionmcmanus/tight
Author: Michael McManus
Author-email: michaeltightmcmanus@gmail.com
License: MIT
Keywords: tight
Platform: UNKNOWN
Classifier: Development Status :: 2 - Pre-Alpha
Classifier: Intended Audience :: Developers
Classifier: License :: OSI Approved :: MIT License
Classifier: Natural Language :: English
Classifier: Programming Language :: Python :: 3
Classifier: Programming Language :: Python :: 3.6
